whatsmate/__init__.py
whatsmate-1.3.dist-info/METADATA
whatsmate-1.3.dist-info/WHEEL
whatsmate-1.3.dist-info/top_level.txt
whatsmate-1.3.dist-info/RECORD
