Metadata-Version: 2.1
Name: whatsmate
Version: 1.3
Summary: The ultimate WhatsApp Wrapper for Python
Home-page: https://github.com/iamharshdev/whatsmate
Author: Harsh Vardhan Goswami
Author-email: me@iamharsh.dev
License: MIT
Keywords: whatsapp automation chatbot api
Classifier: License :: OSI Approved :: MIT License
Classifier: Programming Language :: Python :: 3
Classifier: Programming Language :: Python :: 3.6
Classifier: Programming Language :: Python :: 3.7
Classifier: Programming Language :: Python :: 3.8
Classifier: Programming Language :: Python :: 3.9
Classifier: Topic :: Communications
Classifier: Topic :: Software Development :: Libraries :: Python Modules
